yalp/__init__.py
yalp/config.py
yalp/exceptions.py
yalp/scripts.py
yalp/utils.py
yalp/version.py
yalp/inputs/__init__.py
yalp/inputs/file.py
yalp/inputs/log_handler.py
yalp/outputs/__init__.py
yalp/outputs/elasticsearch.py
yalp/outputs/file.py
yalp/outputs/mongo.py
yalp/outputs/stdout.py
yalp/parsers/__init__.py
yalp/parsers/geoip.py
yalp/parsers/grok.py
yalp/parsers/json.py
yalp/parsers/keyvalue.py
yalp/parsers/passthrough.py
yalp/parsers/regex.py
yalp/parsers/timestamp.py
yalp/parsers/transform.py
yalp/parsers/url.py
yalp/parsers/user_agent.py
yalp/pipeline/__init__.py
yalp/pipeline/tasks.py
yalp/test/__init__.py
yalp/test/testcase.py
yalp/test/utils.py
yalp-1.11.data/scripts/yalp
yalp-1.11.data/scripts/yalp-inputs
yalp-1.11.data/scripts/yalp-parsers
yalp-1.11.data/scripts/yalp-outputers
yalp-1.11.dist-info/top_level.txt
yalp-1.11.dist-info/METADATA
yalp-1.11.dist-info/DESCRIPTION.rst
yalp-1.11.dist-info/metadata.json
yalp-1.11.dist-info/WHEEL
yalp-1.11.dist-info/RECORD
