Metadata-Version: 2.0
Name: yalp
Version: 1.11
Summary: Distributed log parsing and collection.
Home-page: https://github.com/yalp-log/yalp
Author: Timothy Messier
Author-email: tim.messier@gmail.com
License: Apache-2
Platform: UNKNOWN
Classifier: Programming Language :: Python
Classifier: Programming Language :: Python :: 2.7
Classifier: Development Status :: 5 - Production/Stable
Classifier: Intended Audience :: Developers
Classifier: Intended Audience :: System Administrators
Classifier: Environment :: Console
Classifier: License :: OSI Approved :: Apache Software License
Classifier: Operating System :: POSIX :: Linux
Requires-Dist: PyYAML (>=3.11)
Requires-Dist: celery (>=3.1.19)
Requires-Dist: python-dateutil (>=2.4.2)
Requires-Dist: yalp-grok (>=0.3)
Requires-Dist: user-agents (>=1.0.1)
Requires-Dist: ua-parser (>=0.4.1)
